BESS_JPL/BESS_JPL.py
BESS_JPL/C3_photosynthesis.py
BESS_JPL/C4_fraction.jpeg
BESS_JPL/C4_fraction.tif
BESS_JPL/C4_fraction.tif.aux.xml
BESS_JPL/C4_photosynthesis.py
BESS_JPL/ECOv002-cal-val-BESS-JPL-GEOS5FP-inputs.csv
BESS_JPL/ECOv002-cal-val-BESS-JPL-inputs.csv
BESS_JPL/ECOv002-cal-val-BESS-JPL-outputs.csv
BESS_JPL/ECOv002-cal-val-FLiESANN-inputs.csv
BESS_JPL/ECOv002-static-tower-BESS-JPL-inputs.csv
BESS_JPL/ECOv002_calval_BESS_inputs.py
BESS_JPL/ECOv002_static_tower_BESS_inputs.py
BESS_JPL/FVC_from_NDVI.py
BESS_JPL/LAI_from_NDVI.py
BESS_JPL/NDVI_maximum.jpeg
BESS_JPL/NDVI_maximum.tif
BESS_JPL/NDVI_minimum.jpeg
BESS_JPL/NDVI_minimum.tif
BESS_JPL/__init__.py
BESS_JPL/ball_berry_intercept_C3.jpeg
BESS_JPL/ball_berry_intercept_C3.tif
BESS_JPL/ball_berry_slope_C3.jpeg
BESS_JPL/ball_berry_slope_C3.tif
BESS_JPL/ball_berry_slope_C4.jpeg
BESS_JPL/ball_berry_slope_C4.tif
BESS_JPL/calculate_VCmax.py
BESS_JPL/calculate_bulk_aerodynamic_resistance.py
BESS_JPL/calculate_friction_velocity.py
BESS_JPL/canopy_energy_balance.py
BESS_JPL/canopy_longwave_radiation.py
BESS_JPL/canopy_shortwave_radiation.py
BESS_JPL/carbon_uptake_efficiency.jpeg
BESS_JPL/carbon_uptake_efficiency.tif
BESS_JPL/carbon_water_fluxes.py
BESS_JPL/colors.py
BESS_JPL/constants.py
BESS_JPL/exceptions.py
BESS_JPL/generate_BESS_GEOS5FP_inputs.py
BESS_JPL/generate_BESS_inputs_table.py
BESS_JPL/generate_input_dataset.py
BESS_JPL/generate_output_dataset.py
BESS_JPL/interpolate_C3_C4.py
BESS_JPL/kn.jpeg
BESS_JPL/kn.tif
BESS_JPL/load_C4_fraction.py
BESS_JPL/load_NDVI_maximum.py
BESS_JPL/load_NDVI_minimum.py
BESS_JPL/load_ball_berry_intercept_C3.py
BESS_JPL/load_ball_berry_slope_C3.py
BESS_JPL/load_ball_berry_slope_C4.py
BESS_JPL/load_carbon_uptake_efficiency.py
BESS_JPL/load_kn.py
BESS_JPL/load_peakVCmax_C3.py
BESS_JPL/load_peakVCmax_C4.py
BESS_JPL/meteorology.py
BESS_JPL/model.py
BESS_JPL/peakVCmax_C3.jpeg
BESS_JPL/peakVCmax_C3.tif
BESS_JPL/peakVCmax_C4.jpeg
BESS_JPL/peakVCmax_C4.tif
BESS_JPL/process_BESS_table.py
bess_jpl-1.28.0.dist-info/licenses/LICENSE
bess_jpl-1.28.0.dist-info/METADATA
bess_jpl-1.28.0.dist-info/WHEEL
bess_jpl-1.28.0.dist-info/top_level.txt
bess_jpl-1.28.0.dist-info/RECORD
