Metadata-Version: 2.4
Name: BESS-JPL
Version: 1.28.0
Summary: Breathing Earth System Simulator (BESS) Gross Primary Production (GPP) and Evapotranspiration (ET) Model Python
Author-email: Gregory Halverson <gregory.h.halverson@jpl.nasa.gov>
Project-URL: Homepage, https://github.com/JPL-Evapotranspiration-Algorithms/BESS-JPL
Classifier: Programming Language :: Python :: 3
Classifier: Operating System :: OS Independent
Requires-Python: >=3.10
License-File: LICENSE
Requires-Dist: check-distribution>=1.2.0
Requires-Dist: daylight-evapotranspiration
Requires-Dist: ECOv002-calval-tables>=1.6.0
Requires-Dist: FLiESANN>=2.13.0
Requires-Dist: gedi-canopy-height>=1.1.0
Requires-Dist: GEOS5FP>=2.19.0
Requires-Dist: koppengeiger>=1.1.0
Requires-Dist: MODISCI>=1.4.0
Requires-Dist: monte-carlo-sensitivity>=1.5.0
Requires-Dist: NASADEM>=1.3.0
Requires-Dist: numpy
Requires-Dist: pytictoc
Requires-Dist: rasters>=1.9.0
Requires-Dist: seaborn
Requires-Dist: solar-apparent-time>=1.5.3
Provides-Extra: dev
Requires-Dist: build; extra == "dev"
Requires-Dist: pytest>=6.0; extra == "dev"
Requires-Dist: pytest-cov; extra == "dev"
Requires-Dist: jupyter; extra == "dev"
Requires-Dist: pytest; extra == "dev"
Requires-Dist: twine; extra == "dev"
Dynamic: license-file
